stringplus-0.1.1.dist-info/licenses/LICENSE
stringx/__init__.py
stringx/cli.py
stringx/core.py
stringplus-0.1.1.dist-info/METADATA
stringplus-0.1.1.dist-info/WHEEL
stringplus-0.1.1.dist-info/entry_points.txt
stringplus-0.1.1.dist-info/top_level.txt
stringplus-0.1.1.dist-info/RECORD
