Metadata-Version: 2.4
Name: stringplus
Version: 0.1.1
Summary: Extended string utilities with CLI
Author: Ahamed
License: MIT
Keywords: string,text,utils,cli
Requires-Python: >=3.8
License-File: LICENSE
Dynamic: license-file
